bytedbernard/__init__.py
bytedbernard-0.0.1.dist-info/METADATA
bytedbernard-0.0.1.dist-info/WHEEL
bytedbernard-0.0.1.dist-info/top_level.txt
bytedbernard-0.0.1.dist-info/RECORD
