Metadata-Version: 2.1
Name: bytedbernard
Version: 0.0.1
Summary: A simple package named bytedbernard
Home-page: https://github.com/artifact/bytedbernard.git
Author: artifact
Author-email: artifact@example.com
License: UNKNOWN
Platform: UNKNOWN
Classifier: Programming Language :: Python :: 3
Classifier: License :: OSI Approved :: MIT License
Classifier: Operating System :: OS Independent
